agentgraph/__init__.py
agentgraph/config.py
agentgraph/core/__init__.py
agentgraph/core/conversation.py
agentgraph/core/graph.py
agentgraph/core/jinjamanager.py
agentgraph/core/llmmodel.py
agentgraph/core/msgseq.py
agentgraph/core/mutable.py
agentgraph/core/prompts.py
agentgraph/core/reflect.py
agentgraph/core/tools.py
agentgraph/core/var.py
agentgraph/core/vardict.py
agentgraph/core/varset.py
agentgraph/data/__init__.py
agentgraph/data/filestore.py
agentgraph/exec/__init__.py
agentgraph/exec/engine.py
agentgraph/exec/scheduler.py
agentgraph-0.2.dist-info/LICENSE
agentgraph-0.2.dist-info/METADATA
agentgraph-0.2.dist-info/WHEEL
agentgraph-0.2.dist-info/top_level.txt
agentgraph-0.2.dist-info/RECORD
