Metadata-Version: 2.1
Name: agentgraph
Version: 0.2
Summary: A library for task-based parallel programming for Python.  AgentGraph primarily targets AI software that integrates LLM queries (it contains language support generating LLM queries), but can also parallelize tasks that make calls into native code that drops the GIL.  Supports LLM query memoization for fast, cheap debug cycles.
Author: PLRG Team
Author-email: Brian Demsky <bdemsky@uci.edu>, Simon Guo <yutong4@uci.edu>, Conan Truong <cjtruong@uci.edu>
Project-URL: Homepage, https://github.com/bdemsky/agentgraph
Project-URL: Issues, https://github.com/bdemsky/agentgraph/issues
Keywords: LLM,Task parallelism,Nested task parallelism,Large Language Models,Query generation language
Classifier: Programming Language :: Python :: 3
Classifier: License :: OSI Approved :: Apache Software License
Classifier: Operating System :: OS Independent
Requires-Python: >=3.9
License-File: LICENSE
Requires-Dist: asyncio
Requires-Dist: openai
Requires-Dist: jinja2
Requires-Dist: janus
Requires-Dist: tiktoken
